README.md
setup.py
mcenter/__init__.py
mcenter/channels/__init__.py
mcenter/channels/email.py
mcenter/channels/sms_5c.py
mcenter/channels/ws.py
mcenter/channels/ws_redis.py
mcenter/db/__init__.py
mcenter/db/mongo.py
mcenter/http_handler/__init__.py
mcenter/http_handler/msg_tpl_handler.py
mcenter/routes/__init__.py
mcenter/routes/msg_tpl.py
mcenter/routes/ws.py
mcenter/services/__init__.py
mcenter/services/ctrl_msg_tpl.py
mcenter/services/messenger.py
mcenter/services/async_wrap/__init__.py
mcenter/services/async_wrap/ctrl_msg_tpl.py
mcenter/services/async_wrap/messenger.py
mcenter/ws_handler/__init__.py
mcenter/ws_handler/msg_handler.py
ucenter/__init__.py
ucenter/db/__init__.py
ucenter/db/mongo.py
ucenter/http_handler/__init__.py
ucenter/http_handler/user/__init__.py
ucenter/http_handler/user/code_verify.py
ucenter/http_handler/user/identify.py
ucenter/http_handler/user/logout.py
ucenter/http_handler/user/register.py
ucenter/http_handler/user/send_code.py
ucenter/http_handler/user/user_info.py
ucenter/http_handler/user/login/__init__.py
ucenter/http_handler/user/login/with_code.py
ucenter/http_handler/user/login/with_pwd.py
ucenter/http_handler/user/login/with_weixin.py
ucenter/http_handler/user/login/with_wxmp.py
ucenter/http_handler/user/update/__init__.py
ucenter/http_handler/user/update/bind_with_code.py
ucenter/http_handler/user/update/bind_with_weixin.py
ucenter/http_handler/user/update/set_name.py
ucenter/http_handler/user/update/set_password.py
ucenter/http_handler/user/update/unbind_weixin.py
ucenter/http_handler/user/update/update_common.py
ucenter/http_handler/user_manage/__init__.py
ucenter/http_handler/user_manage/user_handler.py
ucenter/routes/__init__.py
ucenter/routes/user.py
ucenter/services/__init__.py
ucenter/services/ctrl_user.py
ucenter/services/permit.py
ucenter/services/uid.py
ucenter/services/user_indicate.py
ucenter/services/verify_code.py
ucenter/services/async_wrap/__init__.py
ucenter/services/async_wrap/ctrl_user.py
web_ucenter.egg-info/PKG-INFO
web_ucenter.egg-info/SOURCES.txt
web_ucenter.egg-info/dependency_links.txt
web_ucenter.egg-info/top_level.txt